pyrotkit/__init__.py
pyrotkit/constants.py
pyrotkit/fov/__init__.py
pyrotkit/fov/precise_permissive.py
pyrotkit/generators/__init__.py
pyrotkit/generators/cellular.py
pyrotkit/generators/mapgen.py
pyrotkit/generators/rectroom.py
pyrotkit/los/__init__.py
pyrotkit/los/bresenham.py
pyrotkit/los/xiaolinwu.py
pyrotkit/path/__init__.py
pyrotkit/path/dijkstra.py
pyrotkit/path/pathfinder.py
pyrotkit/tools/__init__.py
pyrotkit/tools/camera.py
pyrotkit/tools/funcs.py
pyrotkit/types/__init__.py
pyrotkit/types/coordinate.py
pyrotkit/types/pathtile.py
pyrotkit/types/rectroom.py
pyrotkit/types/tile.py
pyrotkit/types/wutile.py
pyrotkit-0.2.0.dist-info/LICENSE
pyrotkit-0.2.0.dist-info/METADATA
pyrotkit-0.2.0.dist-info/WHEEL
pyrotkit-0.2.0.dist-info/top_level.txt
pyrotkit-0.2.0.dist-info/RECORD
