Metadata-Version: 2.1
Name: pyrotkit
Version: 0.2.0
Summary: A library to help with roguelikes
Author-email: J&S Games <ideal.job6119@fastmail.com>
Project-URL: Homepage, https://github.com/elegantiron/pyrotkit
Project-URL: Issues, https://github.com/elegantiron/pyrotkit/issues
Project-URL: Documentation, https://elegantiron.github.io/pyrotkit/
Classifier: Programming Language :: Python :: 3
Classifier: License :: OSI Approved :: MIT License
Classifier: Operating System :: OS Independent
Requires-Python: >=3.12
License-File: LICENSE
Requires-Dist: numpy>=2.2
